togrill_bluetooth/__init__.py
togrill_bluetooth/__main__.py
togrill_bluetooth/client.py
togrill_bluetooth/const.py
togrill_bluetooth/exceptions.py
togrill_bluetooth/packets.py
togrill_bluetooth/py.typed
togrill_bluetooth/services.py
togrill_bluetooth-0.8.1.dist-info/METADATA
togrill_bluetooth-0.8.1.dist-info/WHEEL
togrill_bluetooth-0.8.1.dist-info/entry_points.txt
togrill_bluetooth-0.8.1.dist-info/licenses/LICENSE
togrill_bluetooth-0.8.1.dist-info/RECORD
