Metadata-Version: 2.4
Name: togrill-bluetooth
Version: 0.8.1
Summary: Module to handle communication with ToGrill compatible temperature probes.
Project-URL: Repository, https://github.com/elupus/togrill-bluetooth
Author-email: Joakim Plate <elupus@ecce.se>
License-Expression: MIT
License-File: LICENSE
Classifier: Development Status :: 4 - Beta
Classifier: Intended Audience :: Developers
Classifier: Operating System :: OS Independent
Classifier: Programming Language :: Python
Classifier: Programming Language :: Python :: 3
Classifier: Programming Language :: Python :: 3.11
Classifier: Programming Language :: Python :: 3.12
Classifier: Programming Language :: Python :: 3.13
Classifier: Typing :: Typed
Requires-Python: <4.0,>=3.11
Requires-Dist: bleak-retry-connector>=4.0.0
Requires-Dist: bleak>=1.0.1
Provides-Extra: cli
Requires-Dist: anyio>=4.9.0; extra == 'cli'
Requires-Dist: asyncclick>=8.1.8; extra == 'cli'
